nash_mcp/__init__.py
nash_mcp/constants.py
nash_mcp/execute/__init__.py
nash_mcp/execute/execute_command.py
nash_mcp/execute/execute_python.py
nash_mcp/execute/list_installed_packages.py
nash_mcp/fetch_webpage/__init__.py
nash_mcp/fetch_webpage/fetch_webpage.py
nash_mcp/logging.py
nash_mcp/nash_secrets/__init__.py
nash_mcp/nash_secrets/nash_secrets.py
nash_mcp/nash_tasks/__init__.py
nash_mcp/nash_tasks/nash_tasks.py
nash_mcp/operate_browser/__init__.py
nash_mcp/operate_browser/browser_agent.py
nash_mcp/operate_browser/operate_browser.py
nash_mcp/process_manager.py
nash_mcp/server.py
mseep_nash_mcp-0.1.17.dist-info/LICENSE
mseep_nash_mcp-0.1.17.dist-info/METADATA
mseep_nash_mcp-0.1.17.dist-info/WHEEL
mseep_nash_mcp-0.1.17.dist-info/entry_points.txt
mseep_nash_mcp-0.1.17.dist-info/RECORD
