Metadata-Version: 2.3
Name: mseep-nash-mcp
Version: 0.1.17
Summary: Nash MCP
License: MIT
Author: mseep
Author-email: support@skydeck.ai
Maintainer: mseep
Maintainer-email: support@skydeck.ai
Requires-Python: >=3.11,<4.0
Classifier: License :: OSI Approved :: MIT License
Classifier: Programming Language :: Python :: 3
Classifier: Programming Language :: Python :: 3.11
Classifier: Programming Language :: Python :: 3.12
Classifier: Programming Language :: Python :: 3.13
Requires-Dist: async-timeout (>=5.0.1,<6.0.0)
Requires-Dist: av (>=14.2.0,<15.0.0)
Requires-Dist: beautifulsoup4 (>=4.13.3,<5.0.0)
Requires-Dist: biopython (>=1.85,<2.0)
Requires-Dist: browser-use (>=0.1.40,<0.2.0)
Requires-Dist: chromedriver-autoinstaller (>=0.6.4,<0.7.0)
Requires-Dist: construct (==2.10.68)
Requires-Dist: docx2txt (>=0.8,<0.9)
Requires-Dist: ebooklib (>=0.18,<0.19)
Requires-Dist: eth-utils (>=5.2.0,<6.0.0)
Requires-Dist: ffmpeg-python (>=0.2.0,<0.3.0)
Requires-Dist: geckodriver-autoinstaller (>=0.1.0,<0.2.0)
Requires-Dist: gitpython (>=3.1.44,<4.0.0)
Requires-Dist: h5py (>=3.13.0,<4.0.0)
Requires-Dist: html2text (>=2024.2.26,<2025.0.0)
Requires-Dist: langchain-anthropic (==0.3.3)
Requires-Dist: langchain-openai (==0.3.1)
Requires-Dist: librosa (>=0.11.0,<0.12.0)
Requires-Dist: matplotlib (>=3.10.0,<4.0.0)
Requires-Dist: mcp[cli] (>=1.4.1,<2.0.0)
Requires-Dist: mutagen (>=1.47.0,<2.0.0)
Requires-Dist: netcdf4 (>=1.7.2,<2.0.0)
Requires-Dist: opencv-python (>=4.11.0.86,<5.0.0.0)
Requires-Dist: openpyxl (>=3.1.5,<4.0.0)
Requires-Dist: pandas (>=2.2.3,<3.0.0)
Requires-Dist: pdf2image (>=1.17.0,<2.0.0)
Requires-Dist: playwright (>=1.50.0,<2.0.0)
Requires-Dist: psd-tools (>=1.10.7,<2.0.0)
Requires-Dist: psutil (>=5.9.8,<6.0.0)
Requires-Dist: psycopg2-binary (>=2.9.10,<3.0.0)
Requires-Dist: py7zr (>=0.22.0,<0.23.0)
Requires-Dist: pydicom (>=3.0.1,<4.0.0)
Requires-Dist: pydub (>=0.25.1,<0.26.0)
Requires-Dist: pyelftools (>=0.32,<0.33)
Requires-Dist: pygltflib (>=1.16.3,<2.0.0)
Requires-Dist: pymongo (>=4.11.2,<5.0.0)
Requires-Dist: pypdf (>=5.3.1,<6.0.0)
Requires-Dist: pypdf2 (>=3.0.1,<4.0.0)
Requires-Dist: python-docx (>=1.1.2,<2.0.0)
Requires-Dist: python-dotenv (>=1.0.1,<2.0.0)
Requires-Dist: python-pptx (>=1.0.2,<2.0.0)
Requires-Dist: pywavefront (>=1.3.3,<2.0.0)
Requires-Dist: pyxlsb (>=1.0.10,<2.0.0)
Requires-Dist: rarfile (>=4.2,<5.0)
Requires-Dist: requests (>=2.32.3,<3.0.0)
Requires-Dist: retry (>=0.9.2,<0.10.0)
Requires-Dist: scikit-learn (>=1.6.1,<2.0.0)
Requires-Dist: seaborn (>=0.13.2,<0.14.0)
Requires-Dist: selenium (>=4.29.0,<5.0.0)
Requires-Dist: slugify (>=0.0.1,<0.0.2)
Requires-Dist: solana (>=0.36.6,<0.37.0)
Requires-Dist: solders (>=0.26.0,<0.27.0)
Requires-Dist: sqlalchemy (>=2.0.38,<3.0.0)
Requires-Dist: statsmodels (>=0.14.4,<0.15.0)
Requires-Dist: tabulate (>=0.9.0,<0.10.0)
Requires-Dist: tenacity (>=9.0.0,<10.0.0)
Requires-Dist: tensorflow (>=2.18.0,<3.0.0)
Requires-Dist: torch (>=2.6.0,<3.0.0)
Requires-Dist: trimesh (>=4.6.4,<5.0.0)
Requires-Dist: twisted (>=24.11.0,<25.0.0)
Requires-Dist: web3 (>=7.9.0,<8.0.0)
Requires-Dist: webdriver-manager (>=4.0.2,<5.0.0)
Requires-Dist: xlrd (>=2.0.1,<3.0.0)
Requires-Dist: xlsxwriter (>=3.2.2,<4.0.0)
Requires-Dist: zipfile38 (>=0.0.3,<0.0.4)
